pysic/__init__.py
pysic/engine.py
pysic/errors.py
pysic/pillow_gif_patch.py
py_sic-0.3.0a1.dist-info/LICENSE
py_sic-0.3.0a1.dist-info/METADATA
py_sic-0.3.0a1.dist-info/WHEEL
py_sic-0.3.0a1.dist-info/top_level.txt
py_sic-0.3.0a1.dist-info/RECORD
