Metadata-Version: 2.1
Name: py-sic
Version: 0.3.0a1
Summary: A simple image converter for Python.
Home-page: https://github.com/ArvinZJC/PY-SIC
Author: Arvin Zhao
Author-email: SteveJobz@isarvin.com
License: GPL-3.0 License
Project-URL: Homepage, https://github.com/ArvinZJC/PY-SIC
Project-URL: Documentation, https://github.com/ArvinZJC/PY-SIC
Project-URL: Changelog, https://github.com/ArvinZJC/PY-SIC/releases
Project-URL: Source, https://github.com/ArvinZJC/PY-SIC
Project-URL: Issue Tracker, https://github.com/ArvinZJC/PY-SIC/issues
Keywords: image-converter,pypi-package,python3
Platform: any
Classifier: Intended Audience :: Developers
Classifier: License :: OSI Approved :: GNU General Public License v3 (GPLv3)
Classifier: Natural Language :: English
Classifier: Operating System :: OS Independent
Classifier: Programming Language :: Python
Classifier: Programming Language :: Python :: 3
Classifier: Programming Language :: Python :: 3 :: Only
Classifier: Programming Language :: Python :: 3.6
Classifier: Programming Language :: Python :: 3.7
Classifier: Programming Language :: Python :: 3.8
Classifier: Programming Language :: Python :: 3.9
Classifier: Programming Language :: Python :: 3.10
Classifier: Topic :: Multimedia :: Graphics :: Graphics Conversion
Provides: pysic
Requires-Python: >=3.6
License-File: LICENSE
Requires-Dist: Pillow (>=8.4.0)
Requires-Dist: tqdm (>=4.62.2)
